gitlabcidocs/__init__.py
gitlabcidocs/__main__.py
gitlabcidocs/docsbuilder.py
gitlabcidocs/docsgen.py
gitlabcidocs/errors.py
gitlabcidocs/pipelineparser/__init__.py
gitlabcidocs/pipelineparser/globalvariables.py
gitlabcidocs/pipelineparser/rule.py
gitlabcidocs/pipelineparser/variable.py
gitlabcidocs/pipelineparser/workflow.py
gitlab_ci_docs-0.1.0b3.dist-info/LICENSE
gitlab_ci_docs-0.1.0b3.dist-info/METADATA
gitlab_ci_docs-0.1.0b3.dist-info/WHEEL
gitlab_ci_docs-0.1.0b3.dist-info/top_level.txt
gitlab_ci_docs-0.1.0b3.dist-info/RECORD
